kimai_mcp/__init__.py
kimai_mcp/__main__.py
kimai_mcp/client.py
kimai_mcp/models.py
kimai_mcp/security.py
kimai_mcp/server.py
kimai_mcp/sse_server.py
kimai_mcp/streamable_http_server.py
kimai_mcp/user_config.py
kimai_mcp/tools/__init__.py
kimai_mcp/tools/absence_analytics.py
kimai_mcp/tools/absence_manager.py
kimai_mcp/tools/batch_utils.py
kimai_mcp/tools/calendar_meta.py
kimai_mcp/tools/config_info.py
kimai_mcp/tools/entity_manager.py
kimai_mcp/tools/project_analysis.py
kimai_mcp/tools/rate_manager.py
kimai_mcp/tools/team_access_manager.py
kimai_mcp/tools/timesheet_analytics.py
kimai_mcp/tools/timesheet_consolidated.py
kimai_mcp-2.11.2.dist-info/METADATA
kimai_mcp-2.11.2.dist-info/WHEEL
kimai_mcp-2.11.2.dist-info/entry_points.txt
kimai_mcp-2.11.2.dist-info/licenses/LICENSE
kimai_mcp-2.11.2.dist-info/RECORD
