Metadata-Version: 2.4
Name: kimai-mcp
Version: 2.11.2
Summary: MCP server for Kimai time-tracking API integration
Project-URL: Homepage, https://github.com/glazperle/kimai_mcp
Project-URL: Repository, https://github.com/glazperle/kimai_mcp
Project-URL: Bug Tracker, https://github.com/glazperle/kimai_mcp/issues
Author: Kimai MCP Contributors
License: MIT
License-File: LICENSE
Keywords: api,kimai,mcp,model-context-protocol,time-tracking
Classifier: Development Status :: 4 - Beta
Classifier: Intended Audience :: Developers
Classifier: License :: OSI Approved :: MIT License
Classifier: Programming Language :: Python :: 3
Classifier: Programming Language :: Python :: 3.10
Classifier: Programming Language :: Python :: 3.11
Classifier: Programming Language :: Python :: 3.12
Classifier: Programming Language :: Python :: 3.13
Classifier: Topic :: Software Development :: Libraries :: Python Modules
Requires-Python: >=3.10
Requires-Dist: httpx>=0.24.0
Requires-Dist: mcp>=0.9.0
Requires-Dist: pydantic>=2.0.0
Requires-Dist: python-dotenv>=1.0.0
Provides-Extra: dev
Requires-Dist: black>=23.0.0; extra == 'dev'
Requires-Dist: build>=1.0.0; extra == 'dev'
Requires-Dist: pytest-asyncio>=0.21.0; extra == 'dev'
Requires-Dist: pytest-httpx>=0.21.0; extra == 'dev'
Requires-Dist: pytest>=7.0.0; extra == 'dev'
Requires-Dist: ruff>=0.1.0; extra == 'dev'
Provides-Extra: server
Requires-Dist: fastapi>=0.104.0; extra == 'server'
Requires-Dist: sse-starlette>=1.6.5; extra == 'server'
Requires-Dist: uvicorn[standard]>=0.24.0; extra == 'server'
